deepseek/__init__.py
deepseek/_api.py
deepseek/_chat.py
deepseek/_const.py
deepseek/network/__init__.py
deepseek/network/http.py
deepseek/utils/__init__.py
deepseek/utils/deepseek_hash.py
deepseek/utils/encrypt.py
deepseek/utils/sign.wasm
deepseek/utils/utils.py
py_deepseek_api-1.0.3.dist-info/LICENSE
py_deepseek_api-1.0.3.dist-info/METADATA
py_deepseek_api-1.0.3.dist-info/WHEEL
py_deepseek_api-1.0.3.dist-info/top_level.txt
py_deepseek_api-1.0.3.dist-info/RECORD
