Metadata-Version: 2.2
Name: py-deepseek-api
Version: 1.0.3
Summary: Unoffical DeepSeek API for Python
Home-page: https://github.com/robbinhust/deepseek-api
Author: robbinhust
Classifier: Programming Language :: Python :: 3
Classifier: License :: OSI Approved :: MIT License
Classifier: Operating System :: OS Independent
Requires-Python: >=3.6
License-File: LICENSE
Requires-Dist: requests>=2.32.3
Requires-Dist: safe-dict>=1.0.3
Requires-Dist: wasmtime>=29.0.0
Requires-Dist: pycryptodome>=3.21.0
Dynamic: author
Dynamic: classifier
Dynamic: description
Dynamic: description-content-type
Dynamic: home-page
Dynamic: requires-dist
Dynamic: requires-python
Dynamic: summary
